[
  {
    "week": 1,
    "price": 112.4
  },
  {
    "week": 2,
    "price": 129.26
  },
  {
    "week": 3,
    "price": 143.22
  },
  {
    "week": 4,
    "price": 163.27
  },
  {
    "week": 5,
    "price": 187.76
  },
  {
    "week": 7,
    "price": 103.8
  },
  {
    "week": 8,
    "price": 119.37
  },
  {
    "week": 9,
    "price": 127.49
  },
  {
    "week": 10,
    "price": 141.77
  },
  {
    "week": 11,
    "price": 147.72
  },
  {
    "week": 12,
    "price": 153.33
  },
  {
    "week": 13,
    "price": 176.33
  },
  {
    "week": 5,
    "price": 187.76,
    "open": 176.33,
    "high": 197.148,
    "low": 167.5135,
    "close": 187.76,
    "reason": "STATS"
  },
  {
    "week": 6,
    "price": 197.148,
    "open": 187.76,
    "high": 207.0054,
    "low": 178.37199999999999,
    "close": 197.148,
    "reason": "DNP"
  }
]