[
  {
    "week": 1,
    "price": 115.0
  },
  {
    "week": 2,
    "price": 124.66
  },
  {
    "week": 3,
    "price": 136.13
  },
  {
    "week": 6,
    "price": 108.6
  },
  {
    "week": 7,
    "price": 124.89
  },
  {
    "week": 8,
    "price": 138.13
  },
  {
    "week": 9,
    "price": 158.85
  },
  {
    "week": 11,
    "price": 111.6
  },
  {
    "week": 12,
    "price": 114.5
  },
  {
    "week": 13,
    "price": 116.56
  },
  {
    "week": 5,
    "price": 108.40079999999999,
    "open": 116.56,
    "high": 122.388,
    "low": 102.98075999999999,
    "close": 108.40079999999999,
    "reason": "DNP"
  }
]