[
  {
    "week": 1,
    "price": 115.0
  },
  {
    "week": 2,
    "price": 122.36
  },
  {
    "week": 3,
    "price": 140.71
  },
  {
    "week": 4,
    "price": 146.62
  },
  {
    "week": 8,
    "price": 109.6
  },
  {
    "week": 9,
    "price": 126.04
  },
  {
    "week": 10,
    "price": 134.11
  },
  {
    "week": 11,
    "price": 136.52
  },
  {
    "week": 12,
    "price": 151.26
  },
  {
    "week": 13,
    "price": 152.47
  },
  {
    "week": 15,
    "price": 100.0
  },
  {
    "week": 5,
    "price": 93.0,
    "open": 100.0,
    "high": 105.0,
    "low": 88.35,
    "close": 93.0,
    "reason": "DNP"
  }
]