[
  {
    "week": 1,
    "price": 102.4
  },
  {
    "week": 7,
    "price": 102.8
  },
  {
    "week": 8,
    "price": 118.22
  },
  {
    "week": 10,
    "price": 101.4
  },
  {
    "week": 11,
    "price": 108.3
  },
  {
    "week": 12,
    "price": 110.03
  },
  {
    "week": 15,
    "price": 111.8
  },
  {
    "week": 5,
    "price": 103.97399999999999,
    "open": 111.8,
    "high": 117.39,
    "low": 98.77529999999999,
    "close": 103.97399999999999,
    "reason": "DNP"
  },
  {
    "week": 6,
    "price": 109.17269999999999,
    "open": 103.97399999999999,
    "high": 114.63133499999999,
    "low": 98.77529999999999,
    "close": 109.17269999999999,
    "reason": "DNP"
  }
]