{
  "playerId": 2977187,
  "history": [
    {
      "week": 1,
      "price": 90.0
    },
    {
      "week": 2,
      "price": 99.0
    },
    {
      "week": 3,
      "price": 89.1
    },
    {
      "week": 4,
      "price": 80.19
    },
    {
      "week": 5,
      "price": 73.05
    },
    {
      "week": 6,
      "price": 80.36
    },
    {
      "week": 7,
      "price": 72.32
    },
    {
      "week": 10,
      "price": 69.46
    },
    {
      "week": 11,
      "price": 62.51
    },
    {
      "week": 12,
      "price": 56.26
    },
    {
      "week": 13,
      "price": 50.63
    },
    {
      "week": 14,
      "price": 55.69
    },
    {
      "week": 15,
      "price": 50.12
    }
  ]
}