[
  {
    "gameID": "20251120_BUF@HOU",
    "seasonType": "Regular Season",
    "away": "BUF",
    "gameDate": "20251120",
    "espnID": "401772946",
    "teamIDHome": "13",
    "gameStatus": "Final",
    "gameWeek": "Week 12",
    "teamIDAway": "4",
    "home": "HOU",
    "espnLink": "https://www.espn.com/nfl/boxscore/_/gameId/401772946",
    "cbsLink": "https://www.cbssports.com/nfl/gametracker/boxscore/NFL_20251120_BUF@HOU",
    "gameTime": "8:15p",
    "gameTime_epoch": "1763687700.0",
    "season": "2025",
    "neutralSite": "False",
    "gameStatusCode": "2"
  },
  {
    "gameID": "20251123_ATL@NO",
    "seasonType": "Regular Season",
    "away": "ATL",
    "gameDate": "20251123",
    "espnID": "401772889",
    "teamIDHome": "23",
    "gameStatus": "Final",
    "gameWeek": "Week 12",
    "teamIDAway": "2",
    "home": "NO",
    "espnLink": "https://www.espn.com/nfl/boxscore/_/gameId/401772889",
    "cbsLink": "https://www.cbssports.com/nfl/gametracker/boxscore/NFL_20251123_ATL@NO",
    "gameTime": "4:25p",
    "gameTime_epoch": "1763933100.0",
    "season": "2025",
    "neutralSite": "False",
    "gameStatusCode": "2"
  },
  {
    "gameID": "20251123_CLE@LV",
    "seasonType": "Regular Season",
    "away": "CLE",
    "gameDate": "20251123",
    "espnID": "401772784",
    "teamIDHome": "17",
    "gameStatus": "Final",
    "gameWeek": "Week 12",
    "teamIDAway": "8",
    "home": "LV",
    "espnLink": "https://www.espn.com/nfl/boxscore/_/gameId/401772784",
    "cbsLink": "https://www.cbssports.com/nfl/gametracker/boxscore/NFL_20251123_CLE@LV",
    "gameTime": "4:05p",
    "gameTime_epoch": "1763931900.0",
    "season": "2025",
    "neutralSite": "False",
    "gameStatusCode": "2"
  },
  {
    "gameID": "20251123_MIN@GB",
    "seasonType": "Regular Season",
    "away": "MIN",
    "gameDate": "20251123",
    "espnID": "401772887",
    "teamIDHome": "12",
    "gameStatus": "Final",
    "gameWeek": "Week 12",
    "teamIDAway": "21",
    "home": "GB",
    "espnLink": "https://www.espn.com/nfl/boxscore/_/gameId/401772887",
    "cbsLink": "https://www.cbssports.com/nfl/gametracker/boxscore/NFL_20251123_MIN@GB",
    "gameTime": "1:00p",
    "gameTime_epoch": "1763920800.0",
    "season": "2025",
    "neutralSite": "False",
    "gameStatusCode": "2"
  },
  {
    "gameID": "20251123_NE@CIN",
    "seasonType": "Regular Season",
    "away": "NE",
    "gameDate": "20251123",
    "espnID": "401772781",
    "teamIDHome": "7",
    "gameStatus": "Final",
    "gameWeek": "Week 12",
    "teamIDAway": "22",
    "home": "CIN",
    "espnLink": "https://www.espn.com/nfl/boxscore/_/gameId/401772781",
    "cbsLink": "https://www.cbssports.com/nfl/gametracker/boxscore/NFL_20251123_NE@CIN",
    "gameTime": "1:00p",
    "gameTime_epoch": "1763920800.0",
    "season": "2025",
    "neutralSite": "False",
    "gameStatusCode": "2"
  },
  {
    "gameID": "20251123_NYJ@BAL",
    "seasonType": "Regular Season",
    "away": "NYJ",
    "gameDate": "20251123",
    "espnID": "401772782",
    "teamIDHome": "3",
    "gameStatus": "Final",
    "gameWeek": "Week 12",
    "teamIDAway": "25",
    "home": "BAL",
    "espnLink": "https://www.espn.com/nfl/boxscore/_/gameId/401772782",
    "cbsLink": "https://www.cbssports.com/nfl/gametracker/boxscore/NFL_20251123_NYJ@BAL",
    "gameTime": "1:00p",
    "gameTime_epoch": "1763920800.0",
    "season": "2025",
    "neutralSite": "False",
    "gameStatusCode": "2"
  },
  {
    "gameID": "20251123_PHI@DAL",
    "seasonType": "Regular Season",
    "away": "PHI",
    "gameDate": "20251123",
    "espnID": "401772890",
    "teamIDHome": "9",
    "gameStatus": "Final",
    "gameWeek": "Week 12",
    "teamIDAway": "27",
    "home": "DAL",
    "espnLink": "https://www.espn.com/nfl/boxscore/_/gameId/401772890",
    "cbsLink": "https://www.cbssports.com/nfl/gametracker/boxscore/NFL_20251123_PHI@DAL",
    "gameTime": "4:25p",
    "gameTime_epoch": "1763933100.0",
    "season": "2025",
    "neutralSite": "False",
    "gameStatusCode": "2"
  },
  {
    "gameID": "20251123_PIT@CHI",
    "seasonType": "Regular Season",
    "away": "PIT",
    "gameDate": "20251123",
    "espnID": "401772780",
    "teamIDHome": "6",
    "gameStatus": "Final",
    "gameWeek": "Week 12",
    "teamIDAway": "26",
    "home": "CHI",
    "espnLink": "https://www.espn.com/nfl/boxscore/_/gameId/401772780",
    "cbsLink": "https://www.cbssports.com/nfl/gametracker/boxscore/NFL_20251123_PIT@CHI",
    "gameTime": "1:00p",
    "gameTime_epoch": "1763920800.0",
    "season": "2025",
    "neutralSite": "False",
    "gameStatusCode": "2"
  },
  {
    "gameID": "20251123_SEA@TEN",
    "seasonType": "Regular Season",
    "away": "SEA",
    "gameDate": "20251123",
    "espnID": "401772886",
    "teamIDHome": "31",
    "gameStatus": "Final",
    "gameWeek": "Week 12",
    "teamIDAway": "29",
    "home": "TEN",
    "espnLink": "https://www.espn.com/nfl/boxscore/_/gameId/401772886",
    "cbsLink": "https://www.cbssports.com/nfl/gametracker/boxscore/NFL_20251123_SEA@TEN",
    "gameTime": "1:00p",
    "gameTime_epoch": "1763920800.0",
    "season": "2025",
    "neutralSite": "False",
    "gameStatusCode": "2"
  },
  {
    "gameID": "20251123_TB@LAR",
    "seasonType": "Regular Season",
    "away": "TB",
    "gameDate": "20251123",
    "espnID": "401772929",
    "teamIDHome": "19",
    "gameStatus": "Final",
    "gameWeek": "Week 12",
    "teamIDAway": "30",
    "home": "LAR",
    "espnLink": "https://www.espn.com/nfl/boxscore/_/gameId/401772929",
    "cbsLink": "https://www.cbssports.com/nfl/gametracker/boxscore/NFL_20251123_TB@LAR",
    "gameTime": "8:20p",
    "gameTime_epoch": "1763947200.0",
    "season": "2025",
    "neutralSite": "False",
    "gameStatusCode": "2"
  },
  {
    "gameID": "20251124_CAR@SF",
    "seasonType": "Regular Season",
    "away": "CAR",
    "gameDate": "20251124",
    "espnID": "401772820",
    "teamIDHome": "28",
    "gameStatus": "Final",
    "gameWeek": "Week 12",
    "teamIDAway": "5",
    "home": "SF",
    "espnLink": "https://www.espn.com/nfl/boxscore/_/gameId/401772820",
    "cbsLink": "https://www.cbssports.com/nfl/gametracker/boxscore/NFL_20251124_CAR@SF",
    "gameTime": "8:15p",
    "gameTime_epoch": "1764033300.0",
    "season": "2025",
    "neutralSite": "False",
    "gameStatusCode": "2"
  }
]